[
  {"id":"flag_21201","type":"flag","difficulty":"medium","questionText":"¿De qué país es esta bandera?","correctAnswer":"Bolivia","options":["Colombia","Perú","Venezuela","Bolivia"],"imageUrl":"https://flagcdn.com/w320/bo.png","extraData":{"countryCode":"bo","countryName":"Bolivia"}},
  {"id":"flag_21202","type":"flag","difficulty":"hard","questionText":"¿De qué país es esta bandera?","correctAnswer":"Albania","options":["Macedonia del Norte","Serbia","Montenegro","Albania"],"imageUrl":"https://flagcdn.com/w320/al.png","extraData":{"countryCode":"al","countryName":"Albania"}},
  {"id":"flag_21203","type":"flag","difficulty":"easy","questionText":"¿De qué país es esta bandera?","correctAnswer":"Corea del Sur","options":["Japón","China","Vietnam","Corea del Sur"],"imageUrl":"https://flagcdn.com/w320/kr.png","extraData":{"countryCode":"kr","countryName":"Corea del Sur"}},
  {"id":"flag_21204","type":"flag","difficulty":"medium","questionText":"¿De qué país es esta bandera?","correctAnswer":"Tanzania","options":["Kenia","Uganda","Mozambique","Tanzania"],"imageUrl":"https://flagcdn.com/w320/tz.png","extraData":{"countryCode":"tz","countryName":"Tanzania"}},
  {"id":"flag_21205","type":"flag","difficulty":"hard","questionText":"¿De qué país es esta bandera?","correctAnswer":"Uzbekistán","options":["Kazajistán","Turkmenistán","Kirguistán","Uzbekistán"],"imageUrl":"https://flagcdn.com/w320/uz.png","extraData":{"countryCode":"uz","countryName":"Uzbekistán"}},
  {"id":"flag_21206","type":"flag","difficulty":"easy","questionText":"¿De qué país es esta bandera?","correctAnswer":"Rusia","options":["Francia","Países Bajos","Luxemburgo","Rusia"],"imageUrl":"https://flagcdn.com/w320/ru.png","extraData":{"countryCode":"ru","countryName":"Rusia"}},
  {"id":"flag_21207","type":"flag","difficulty":"medium","questionText":"¿De qué país es esta bandera?","correctAnswer":"Camboya","options":["Vietnam","Laos","Tailandia","Camboya"],"imageUrl":"https://flagcdn.com/w320/kh.png","extraData":{"countryCode":"kh","countryName":"Camboya"}},
  {"id":"flag_21208","type":"flag","difficulty":"hard","questionText":"¿De qué país es esta bandera?","correctAnswer":"Bosnia y Herzegovina","options":["Croacia","Serbia","Eslovenia","Bosnia y Herzegovina"],"imageUrl":"https://flagcdn.com/w320/ba.png","extraData":{"countryCode":"ba","countryName":"Bosnia y Herzegovina"}},
  {"id":"flag_21209","type":"flag","difficulty":"easy","questionText":"¿De qué país es esta bandera?","correctAnswer":"Grecia","options":["Chipre","Finlandia","Uruguay","Grecia"],"imageUrl":"https://flagcdn.com/w320/gr.png","extraData":{"countryCode":"gr","countryName":"Grecia"}},
  {"id":"flag_21210","type":"flag","difficulty":"medium","questionText":"¿De qué país es esta bandera?","correctAnswer":"Ruanda","options":["Burundi","Uganda","Congo","Ruanda"],"imageUrl":"https://flagcdn.com/w320/rw.png","extraData":{"countryCode":"rw","countryName":"Ruanda"}},
  {"id":"capital_21211","type":"capital","difficulty":"easy","questionText":"¿Cuál es la capital de Estados Unidos?","correctAnswer":"Washington D.C.","options":["Nueva York","Los Ángeles","Washington D.C.","Chicago"],"extraData":{"countryCode":"us","countryName":"Estados Unidos"}},
  {"id":"capital_21212","type":"capital","difficulty":"medium","questionText":"¿Cuál es la capital de Túnez?","correctAnswer":"Túnez","options":["Sfax","Susa","Túnez","Sidi Bou Said"],"extraData":{"countryCode":"tn","countryName":"Túnez"}},
  {"id":"capital_21213","type":"capital","difficulty":"hard","questionText":"¿Cuál es la capital de Guinea-Bisáu?","correctAnswer":"Bisáu","options":["Bafatá","Bisáu","Gabú","Cacheu"],"extraData":{"countryCode":"gw","countryName":"Guinea-Bisáu"}},
  {"id":"capital_21214","type":"capital","difficulty":"medium","questionText":"¿Cuál es la capital de Albania?","correctAnswer":"Tirana","options":["Durrës","Vlorë","Tirana","Elbasan"],"extraData":{"countryCode":"al","countryName":"Albania"}},
  {"id":"capital_21215","type":"capital","difficulty":"hard","questionText":"¿Cuál es la capital de Mauritania?","correctAnswer":"Nuakchott","options":["Nouadhibou","Nuakchott","Rosso","Kiffa"],"extraData":{"countryCode":"mr","countryName":"Mauritania"}},
  {"id":"capital_21216","type":"capital","difficulty":"easy","questionText":"¿Cuál es la capital de México?","correctAnswer":"Ciudad de México","options":["Guadalajara","Monterrey","Cancún","Ciudad de México"],"extraData":{"countryCode":"mx","countryName":"México"}},
  {"id":"capital_21217","type":"capital","difficulty":"medium","questionText":"¿Cuál es la capital de Bulgaria?","correctAnswer":"Sofía","options":["Plovdiv","Varna","Sofía","Burgas"],"extraData":{"countryCode":"bg","countryName":"Bulgaria"}},
  {"id":"capital_21218","type":"capital","difficulty":"hard","questionText":"¿Cuál es la capital de Gambia?","correctAnswer":"Banjul","options":["Serrekunda","Banjul","Brikama","Bakau"],"extraData":{"countryCode":"gm","countryName":"Gambia"}},
  {"id":"capital_21219","type":"capital","difficulty":"easy","questionText":"¿Cuál es la capital de Alemania?","correctAnswer":"Berlín","options":["Múnich","Hamburgo","Fráncfort","Berlín"],"extraData":{"countryCode":"de","countryName":"Alemania"}},
  {"id":"capital_21220","type":"capital","difficulty":"medium","questionText":"¿Cuál es la capital de Jordania?","correctAnswer":"Amán","options":["Aqaba","Irbid","Amán","Zarqa"],"extraData":{"countryCode":"jo","countryName":"Jordania"}},
  {"id":"population_21221","type":"population","difficulty":"easy","questionText":"¿Qué país tiene más población?","correctAnswer":"Nigeria","options":["Sudáfrica","Nigeria"],"extraData":{"countries":["Sudáfrica","Nigeria"],"population1":60414495,"population2":223804632}},
  {"id":"population_21222","type":"population","difficulty":"medium","questionText":"¿Qué país tiene más población?","correctAnswer":"Argelia","options":["Canadá","Argelia"],"extraData":{"countries":["Canadá","Argelia"],"population1":38781292,"population2":45606480}},
  {"id":"population_21223","type":"population","difficulty":"hard","questionText":"¿Qué país tiene más población?","correctAnswer":"Burkina Faso","options":["Grecia","Burkina Faso"],"extraData":{"countries":["Grecia","Burkina Faso"],"population1":10341277,"population2":22673762}},
  {"id":"population_21224","type":"population","difficulty":"hard","questionText":"¿Qué país tiene más población?","correctAnswer":"Cuba","options":["Hungría","Cuba"],"extraData":{"countries":["Hungría","Cuba"],"population1":9597085,"population2":11194449}},
  {"id":"population_21225","type":"population","difficulty":"medium","questionText":"¿Qué país tiene más población?","correctAnswer":"Colombia","options":["España","Colombia"],"extraData":{"countries":["España","Colombia"],"population1":47519628,"population2":52085168}},
  {"id":"area_21226","type":"area","difficulty":"medium","questionText":"¿Qué país es más extenso?","correctAnswer":"Arabia Saudí","options":["México","Arabia Saudí"],"extraData":{"countries":["México","Arabia Saudí"],"area1":1964375,"area2":2149690}},
  {"id":"area_21227","type":"area","difficulty":"hard","questionText":"¿Qué país es más extenso?","correctAnswer":"Nepal","options":["Bangladés","Nepal"],"extraData":{"countries":["Bangladés","Nepal"],"area1":148460,"area2":147516}},
  {"id":"area_21228","type":"area","difficulty":"easy","questionText":"¿Qué país es más extenso?","correctAnswer":"India","options":["México","India"],"extraData":{"countries":["México","India"],"area1":1964375,"area2":3287263}},
  {"id":"area_21229","type":"area","difficulty":"hard","questionText":"¿Qué país es más extenso?","correctAnswer":"Eritrea","options":["Portugal","Eritrea"],"extraData":{"countries":["Portugal","Eritrea"],"area1":92212,"area2":117600}},
  {"id":"area_21230","type":"area","difficulty":"medium","questionText":"¿Qué país es más extenso?","correctAnswer":"Congo (RDC)","options":["Argelia","Congo (RDC)"],"extraData":{"countries":["Argelia","Congo (RDC)"],"area1":2381741,"area2":2344858}},
  {"id":"language_21231","type":"language","difficulty":"medium","questionText":"¿Cuál es el idioma oficial de Kuwait?","correctAnswer":"Árabe","options":["Persa","Inglés","Urdu","Árabe"],"extraData":{"countryCode":"kw","countryName":"Kuwait","languageCode":"ara"}},
  {"id":"language_21232","type":"language","difficulty":"hard","questionText":"¿Cuál es el idioma oficial de Ruanda?","correctAnswer":"Kinyarwanda","options":["Francés","Inglés","Suajili","Kinyarwanda"],"extraData":{"countryCode":"rw","countryName":"Ruanda","languageCode":"kin"}},
  {"id":"language_21233","type":"language","difficulty":"hard","questionText":"¿Cuál es el idioma oficial de Mozambique?","correctAnswer":"Portugués","options":["Inglés","Suajili","Español","Portugués"],"extraData":{"countryCode":"mz","countryName":"Mozambique","languageCode":"por"}},
  {"id":"language_21234","type":"language","difficulty":"medium","questionText":"¿Cuál es el idioma oficial de Yemen?","correctAnswer":"Árabe","options":["Persa","Somalí","Hebreo","Árabe"],"extraData":{"countryCode":"ye","countryName":"Yemen","languageCode":"ara"}},
  {"id":"language_21235","type":"language","difficulty":"easy","questionText":"¿Cuál es el idioma oficial de Estados Unidos?","correctAnswer":"Inglés","options":["Español","Francés","Alemán","Inglés"],"extraData":{"countryCode":"us","countryName":"Estados Unidos","languageCode":"eng"}},
  {"id":"currency_21236","type":"currency","difficulty":"hard","questionText":"¿Cuál es la moneda de Nepal?","correctAnswer":"Rupia nepalí","options":["Rupia india","Taka bangladesí","Rupia nepalí","Rupia pakistaní"],"extraData":{"countryCode":"np","countryName":"Nepal","currencyCode":"NPR"}},
  {"id":"currency_21237","type":"currency","difficulty":"medium","questionText":"¿Cuál es la moneda de Hungría?","correctAnswer":"Florín húngaro","options":["Corona checa","Zloty polaco","Leu rumano","Florín húngaro"],"extraData":{"countryCode":"hu","countryName":"Hungría","currencyCode":"HUF"}},
  {"id":"currency_21238","type":"currency","difficulty":"hard","questionText":"¿Cuál es la moneda de Bolivia?","correctAnswer":"Boliviano","options":["Peso colombiano","Sol peruano","Guaraní paraguayo","Boliviano"],"extraData":{"countryCode":"bo","countryName":"Bolivia","currencyCode":"BOB"}},
  {"id":"currency_21239","type":"currency","difficulty":"medium","questionText":"¿Cuál es la moneda de Malasia?","correctAnswer":"Ringgit malayo","options":["Rupia indonesia","Baht tailandés","Dólar de Singapur","Ringgit malayo"],"extraData":{"countryCode":"my","countryName":"Malasia","currencyCode":"MYR"}},
  {"id":"currency_21240","type":"currency","difficulty":"easy","questionText":"¿Cuál es la moneda de Brasil?","correctAnswer":"Real brasileño","options":["Peso argentino","Peso mexicano","Dólar","Real brasileño"],"extraData":{"countryCode":"br","countryName":"Brasil","currencyCode":"BRL"}},
  {"id":"region_21241","type":"region","difficulty":"easy","questionText":"¿En qué región se encuentra Sudáfrica?","correctAnswer":"África","options":["América","Asia","Europa","África"],"extraData":{"countryCode":"za","countryName":"Sudáfrica","region":"Africa","regionSpanish":"África"}},
  {"id":"region_21242","type":"region","difficulty":"medium","questionText":"¿En qué región se encuentra Tayikistán?","correctAnswer":"Asia","options":["Europa","América","África","Asia"],"extraData":{"countryCode":"tj","countryName":"Tayikistán","region":"Asia","regionSpanish":"Asia"}},
  {"id":"region_21243","type":"region","difficulty":"hard","questionText":"¿En qué región se encuentra Seychelles?","correctAnswer":"África","options":["Asia","América","Oceanía","África"],"extraData":{"countryCode":"sc","countryName":"Seychelles","region":"Africa","regionSpanish":"África"}},
  {"id":"region_21244","type":"region","difficulty":"hard","questionText":"¿En qué región se encuentra Micronesia?","correctAnswer":"Oceanía","options":["Asia","América","África","Oceanía"],"extraData":{"countryCode":"fm","countryName":"Micronesia","region":"Oceania","regionSpanish":"Oceanía"}},
  {"id":"region_21245","type":"region","difficulty":"medium","questionText":"¿En qué región se encuentra Portugal?","correctAnswer":"Europa","options":["América","Asia","África","Europa"],"extraData":{"countryCode":"pt","countryName":"Portugal","region":"Europe","regionSpanish":"Europa"}},
  {"id":"region_21246","type":"region","difficulty":"easy","questionText":"¿En qué región se encuentra Australia?","correctAnswer":"Oceanía","options":["Asia","América","Europa","Oceanía"],"extraData":{"countryCode":"au","countryName":"Australia","region":"Oceania","regionSpanish":"Oceanía"}},
  {"id":"region_21247","type":"region","difficulty":"medium","questionText":"¿En qué región se encuentra Uganda?","correctAnswer":"África","options":["Asia","América","Europa","África"],"extraData":{"countryCode":"ug","countryName":"Uganda","region":"Africa","regionSpanish":"África"}},
  {"id":"region_21248","type":"region","difficulty":"hard","questionText":"¿En qué región se encuentra Dominica?","correctAnswer":"América","options":["Europa","Asia","África","América"],"extraData":{"countryCode":"dm","countryName":"Dominica","region":"Americas","regionSpanish":"América"}},
  {"id":"region_21249","type":"region","difficulty":"easy","questionText":"¿En qué región se encuentra Francia?","correctAnswer":"Europa","options":["América","Asia","África","Europa"],"extraData":{"countryCode":"fr","countryName":"Francia","region":"Europe","regionSpanish":"Europa"}},
  {"id":"region_21250","type":"region","difficulty":"medium","questionText":"¿En qué región se encuentra Camboya?","correctAnswer":"Asia","options":["Oceanía","América","África","Asia"],"extraData":{"countryCode":"kh","countryName":"Camboya","region":"Asia","regionSpanish":"Asia"}}
]